captcha/__init__.py
captcha/exceptions.py
captcha/solver.py
captcha/utils.py
master_scramazon/AmazonScraper.py
master_scramazon/__init__.py
master_scramazon-0.1.1.dist-info/METADATA
master_scramazon-0.1.1.dist-info/WHEEL
master_scramazon-0.1.1.dist-info/top_level.txt
master_scramazon-0.1.1.dist-info/RECORD
