Metadata-Version: 2.4
Name: master_scramazon
Version: 0.1.1
Home-page: https://github.com/mehran-sfz/Amazon-Scraper
Author: Mehran Safarzadeh
Requires-Dist: beautifulsoup4>=4.13.3
Requires-Dist: requests>=2.32.3
Requires-Dist: pillow>=11.2.0
Requires-Dist: selenium>=4.30.0
Dynamic: author
Dynamic: description
Dynamic: description-content-type
Dynamic: home-page
Dynamic: requires-dist
